MANIFEST.in
README.md
setup.py
Browthon_Reborn.egg-info/PKG-INFO
Browthon_Reborn.egg-info/SOURCES.txt
Browthon_Reborn.egg-info/dependency_links.txt
Browthon_Reborn.egg-info/entry_points.txt
Browthon_Reborn.egg-info/requires.txt
Browthon_Reborn.egg-info/top_level.txt
browthon/__init__.py
browthon/browthon_app.py
browthon/logo.png
browthon/Addons/__init__.py
browthon/Addons/discord/__init__.py
browthon/Addons/discord/addon.json
browthon/Addons/discord/discord.py
browthon/Addons/discord/logo.png
browthon/Core/__init__.py
browthon/Core/browser.py
browthon/Core/Utils/__init__.py
browthon/Core/Utils/addonsUtils.py
browthon/Core/Utils/contextMenu.py
browthon/Core/Utils/dateUtils.py
browthon/Core/Utils/dbUtils.py
browthon/Core/Utils/downloadUtils.py
browthon/Core/Utils/themeUtils.py
browthon/Core/Utils/urlUtils.py
browthon/Core/Utils/webHitTestResult.py
browthon/Core/Widgets/__init__.py
browthon/Core/Widgets/addonWidget.py
browthon/Core/Widgets/browserWidget.py
browthon/Core/Widgets/downloadWidget.py
browthon/Core/Widgets/listWidget.py
browthon/Core/Widgets/pushButton.py
browthon/Core/Widgets/tabWidget.py
browthon/Core/Widgets/urlInput.py
browthon/Core/Windows/__init__.py
browthon/Core/Windows/parameterWindow.py
browthon/Core/Windows/ParametersPages/__init__.py
browthon/Core/Windows/ParametersPages/addonsPage.py
browthon/Core/Windows/ParametersPages/bookmarksPage.py
browthon/Core/Windows/ParametersPages/downloadPage.py
browthon/Core/Windows/ParametersPages/generalPage.py
browthon/Core/Windows/ParametersPages/historyPage.py
browthon/Core/Windows/ParametersPages/informationsPage.py
browthon/Core/Windows/ParametersPages/raccourcisPage.py
browthon/Core/Windows/ParametersPages/sessionsPage.py
browthon/Core/Windows/ParametersPages/themesPage.py
browthon/Icons/NavigationBar/back.png
browthon/Icons/NavigationBar/forward.png
browthon/Icons/NavigationBar/home.png
browthon/Icons/NavigationBar/noFav.png
browthon/Icons/NavigationBar/param.png
browthon/Icons/NavigationBar/reload.png
browthon/Icons/NavigationBar/yesFav.png
browthon/Icons/Parameters/Addons.png
browthon/Icons/Parameters/Download.png
browthon/Icons/Parameters/Fav.png
browthon/Icons/Parameters/General.png
browthon/Icons/Parameters/History.png
