Metadata-Version: 1.1
Name: Browthon-Reborn
Version: 1.0.1
Summary: A webbrowser made with Python and PySide2
Home-page: https://github.com/Browthon/Browthon-Reborn
Author: LavaPower
Author-email: lavapower84@gmail.com
License: GNU GPLv3
Platform: UNKNOWN
Classifier: Development Status :: 5 - Production/Stable
Classifier: Natural Language :: French
Classifier: Operating System :: OS Independent
Classifier: Programming Language :: Python
Classifier: Programming Language :: Python :: 3
Classifier: Programming Language :: Python :: 3.7
Classifier: Topic :: Internet :: WWW/HTTP :: Browsers
